helga_quip/__init__.py
helga_quip/plugin.py
helga_quip-1.2.0.dist-info/DESCRIPTION.rst
helga_quip-1.2.0.dist-info/METADATA
helga_quip-1.2.0.dist-info/RECORD
helga_quip-1.2.0.dist-info/WHEEL
helga_quip-1.2.0.dist-info/entry_points.txt
helga_quip-1.2.0.dist-info/metadata.json
helga_quip-1.2.0.dist-info/top_level.txt
helga_quip-1.2.0.dist-info/zip-safe
tests/__init__.py
tests/test_plugin.py
