Metadata-Version: 2.0
Name: helga-quip
Version: 1.2.0
Summary: Match quips and other witticisms
Home-page: https://github.com/narfman0/helga-quip
Author: Jon Robison
Author-email: narfman0@gmail.com
License: LICENSE
Keywords: irc bot quip joke jokes
Platform: UNKNOWN
Classifier: Development Status :: 4 - Beta
Classifier: Topic :: Communications :: Chat :: Internet Relay Chat
Classifier: License :: OSI Approved :: GNU General Public License v3 (GPLv3)
Classifier: Operating System :: OS Independent
Classifier: Programming Language :: Python
Classifier: Topic :: Software Development :: Libraries :: Python Modules
Classifier: Topic :: Communications :: Chat :: Internet Relay Chat
Requires-Dist: helga
Requires-Dist: requests
